git_empty_dirs/__init__.py
git_empty_dirs/__main__.py
git_empty_dirs-0.7.dist-info/DESCRIPTION.rst
git_empty_dirs-0.7.dist-info/METADATA
git_empty_dirs-0.7.dist-info/RECORD
git_empty_dirs-0.7.dist-info/WHEEL
git_empty_dirs-0.7.dist-info/entry_points.txt
git_empty_dirs-0.7.dist-info/metadata.json
git_empty_dirs-0.7.dist-info/top_level.txt
