Metadata-Version: 2.0
Name: git-empty-dirs
Version: 0.7
Summary: Committing Empty Directories to Git Repository.
Home-page: https://github.com/ParikhMeet/GitEmptyDirs
Author: Meet Parikh
Author-email: meet.parikh@gmail.com
License: gpl-2.0
Download-URL: https://github.com/ParikhMeet/GitEmptyDirs/archive/v0.7.tar.gz
Keywords: Git,Empty,Directory,Directories,Folder
Platform: UNKNOWN
Classifier: Development Status :: 5 - Production/Stable
Classifier: Intended Audience :: Developers
Classifier: Topic :: Software Development :: Build Tools
Classifier: License :: OSI Approved :: GNU General Public License v2 (GPLv2)
Classifier: Programming Language :: Python :: 3
Classifier: Programming Language :: Python :: 3.2
Classifier: Programming Language :: Python :: 3.3
Classifier: Programming Language :: Python :: 3.4
Classifier: Programming Language :: Python :: 3.5
Classifier: Programming Language :: Python :: 3.6
Classifier: Programming Language :: Python :: 3.7
Classifier: Programming Language :: Python :: 3.8
